scrapeddit/__init__.py
scrapeddit/authentication.py
scrapeddit/models.py
scrapeddit/redditdl.py
scrapeddit/scrapeonce.py
scrapeddit/showit.py
scrapeddit/transforms.py
scrapeddit-0.3.7.dist-info/LICENSE.txt
scrapeddit-0.3.7.dist-info/METADATA
scrapeddit-0.3.7.dist-info/WHEEL
scrapeddit-0.3.7.dist-info/top_level.txt
scrapeddit-0.3.7.dist-info/RECORD
