Metadata-Version: 2.1
Name: scrapeddit
Version: 0.3.7
Summary: Simple test package
Home-page: https://github.com/Mafaz03/scrapeddit
Author: Mafaz03
Author-email: mohdmafaz200303@gmail.com
License-File: LICENSE.txt
Requires-Dist: praw
Requires-Dist: torchinfo
